{
    "header": {
        "title": "Syntaxe JSON",
        "author": "Fornes Leo",
        "date": "2024-01-01"
    },
    "body": [
        [
            "This document is a simple example of the JSON syntax."
        ],
        [
            "Every syntax element is displayed in this document."
        ],
        {
            "section": {
                "title": "header 1",
                "content": [
                    [
                        "This is a basic paragraph with text."
                    ]
                ]
            }
        }
    ]
}